cryotypes/__init__.py
cryotypes/_version.py
cryotypes/image/__init__.py
cryotypes/image/_protocol.py
cryotypes/image/_validators.py
cryotypes/poseset/__init__.py
cryotypes/poseset/_protocol.py
cryotypes/poseset/_utils.py
cryotypes/poseset/_validators.py
cryotypes/projectionmodel/__init__.py
cryotypes/projectionmodel/_data_labels.py
cryotypes/projectionmodel/_transformations.py
cryotypes/projectionmodel/_typing.py
cryotypes/projectionmodel/_utils.py
cryotypes-0.2.0.dist-info/LICENSE
cryotypes-0.2.0.dist-info/METADATA
cryotypes-0.2.0.dist-info/WHEEL
cryotypes-0.2.0.dist-info/top_level.txt
cryotypes-0.2.0.dist-info/RECORD
